<?xml version="1.0" encoding="UTF-8" standalone="no"?>
<pao xmlns:xsi="http://www.w3.org/2001/XMLSchema-instance" paoType="NEUTRAL_MONITOR" displayGroup="Grid Advisor" displayName="Capacitor Bank Neutral Monitor" xsi:noNamespaceSchemaLocation="../pao.xsd">
    <pointFiles>
        <pointFile>NEUTRAL_MONITOR.xml</pointFile>
    </pointFiles>
    <pointInfos>
        <pointInfo name="Battery Voltage" init="true"/>
        <pointInfo name="BER" init="true"/>
        <pointInfo name="Calibrated"/>
        <pointInfo name="Current Survey" init="true"/>
        <pointInfo name="Device Temperature" init="true"/>
        <pointInfo name="High Alert Setpoint"/>
        <pointInfo name="Max Current - Period" init="true"/>
        <pointInfo name="Max Current - Report" init="true"/>
        <pointInfo name="Min Current - Period" init="true"/>
        <pointInfo name="Min Current - Report" init="true"/>
        <pointInfo name="Over Current" init="true"/>
        <pointInfo name="Period Rate"/>
        <pointInfo name="Reed Switch Communication" init="true"/>
        <pointInfo name="Reset Alert Setpoint"/>
        <pointInfo name="Reset Over Current" init="true"/>
        <pointInfo name="RSSI" init="true"/>
        <pointInfo name="Signal Strength" init="true"/>
    </pointInfos>
</pao>
