<?xml version="1.0" encoding="UTF-8" ?>
<!DOCTYPE properties SYSTEM "http://java.sun.com/dtd/properties.dtd">
<properties>
    <!-- Contextual Menu Entries (name of the beans in applicationContext.xml) -->
    <entry key="yukon.web.modules.common.contextualMenu.menuItemAmrArchivedDataExporter">Data Export</entry>
    <entry key="yukon.web.modules.common.contextualMenu.menuItemBulkCollectionAction">Other Actions</entry>
    <entry key="yukon.web.modules.common.contextualMenu.menuItemMapDevices">Map Devices</entry>
    <entry key="yukon.web.modules.common.contextualMenu.menuItemBulkConfigAssign">Assign Config</entry>
    <entry key="yukon.web.modules.common.contextualMenu.menuItemBulkConfigRead">Read Config</entry>
    <entry key="yukon.web.modules.common.contextualMenu.menuItemBulkConfigSend">Send Config</entry>
    <entry key="yukon.web.modules.common.contextualMenu.menuItemBulkConfigVerify">Verify Config</entry>
    <entry key="yukon.web.modules.common.contextualMenu.menuItemBulkDataAnalysis">Data Analysis</entry>
    <entry key="yukon.web.modules.common.contextualMenu.menuItemBulkDeviceCollectionReport">Device Report</entry>
    <entry key="yukon.web.modules.common.contextualMenu.menuItemBulkGroupAdd">Add To Group</entry>
    <entry key="yukon.web.modules.common.contextualMenu.menuItemBulkGroupRemove">Remove From Group</entry>
    <entry key="yukon.web.modules.common.contextualMenu.menuItemBulkMassChange">Mass Change</entry>
    <entry key="yukon.web.modules.common.contextualMenu.menuItemBulkMassDelete">Mass Delete</entry>
    <entry key="yukon.web.modules.common.contextualMenu.menuItemBulkPointsAdd">Add Points</entry>
    <entry key="yukon.web.modules.common.contextualMenu.menuItemBulkPointsRemove">Remove Points</entry>
    <entry key="yukon.web.modules.common.contextualMenu.menuItemBulkPointsUpdate">Update Points</entry>
    <entry key="yukon.web.modules.common.contextualMenu.menuItemBulkRouteLocate">Locate Route</entry>
    <entry key="yukon.web.modules.common.contextualMenu.menuItemGroupCommander">Send Command</entry>
    <entry key="yukon.web.modules.common.contextualMenu.menuItemGroupMeterRead">Read Attribute</entry>
    <entry key="yukon.web.modules.common.contextualMenu.menuItemMeterDetail">View Details</entry>
    <entry key="yukon.web.modules.common.contextualMenu.menuItemRelayDetail">View Details</entry>

    <!-- Text for dropdown container's (instead of the cog); see dropdown.tag  -->
    <entry key="yukon.web.modules.common.contextualMenu.actions">Actions</entry>

</properties>